{
  "name": "zafu",
  "repo_uri": "https://github.com/johnynek/zafu/",
  "doc_base_url": "https://johnynek.github.io/zafu",
  "next_version": "0.0.1",
  "exported_packages": [
    "Zafu/Abstract/Applicative",
    "Zafu/Abstract/Eq",
    "Zafu/Abstract/Foldable",
    "Zafu/Abstract/Hash",
    "Zafu/Abstract/Instances/Predef",
    "Zafu/Abstract/Monad",
    "Zafu/Abstract/Monoid",
    "Zafu/Abstract/Ord",
    "Zafu/Abstract/Semigroup",
    "Zafu/Abstract/Traverse",
    "Zafu/Benchmark/Game/BinaryTrees",
    "Zafu/Benchmark/Game/FannkuchRedux",
    "Zafu/Benchmark/Game/Harness",
    "Zafu/Benchmark/Game/Mandelbrot",
    "Zafu/Benchmark/Vector",
    "Zafu/Collection/Chain",
    "Zafu/Collection/Deque",
    "Zafu/Collection/HashMap",
    "Zafu/Collection/HashSet",
    "Zafu/Collection/Heap",
    "Zafu/Collection/LazyList",
    "Zafu/Collection/LazyTree",
    "Zafu/Collection/List",
    "Zafu/Collection/NonEmptyChain",
    "Zafu/Collection/NonEmptyList",
    "Zafu/Collection/Vector",
    "Zafu/Control/IterState",
    "Zafu/Control/PartialResult",
    "Zafu/Control/Result",
    "Zafu/Testing/HedgeHog",
    "Zafu/Testing/HedgeHog/Range",
    "Zafu/Testing/HedgeHog/Seed",
    "Zafu/Testing/HedgeHog/Size",
    "Zafu/Text/Parse",
    "Zafu/Text/Parse/Error",
    "Zafu/Text/Parse/Types",
    "Zafu/Text/Parse/Rfc5234",
    "Zafu/Text/Pretty",
    "Zafu/Tool/Cat",
    "Zafu/Tool/JsonFormat"
  ],
  "all_packages": [
    ".*"
  ],
  "public_deps": {
    "core_alpha": {
      "version": "6.0.5",
      "hashes": [
        "blake3:c2ce54e411c94b8097ba7dd26606285cc67728ad83d9f9b2045bcc7e85ce039b"
      ],
      "uris": [
        "https://github.com/johnynek/bosatsu/releases/download/v0.0.62/core_alpha-v6.0.5.bosatsu_lib"
      ]
    }
  }
}
